MANIFEST.in
setup.py
PJs.egg-info/PKG-INFO
PJs.egg-info/SOURCES.txt
PJs.egg-info/dependency_links.txt
PJs.egg-info/requires.txt
PJs.egg-info/top_level.txt
pjs/__init__.py
pjs/assign.py
pjs/atomic.py
pjs/blocks.py
pjs/converter.py
pjs/declared.py
pjs/errors.py
pjs/expression.py
pjs/imports.py
pjs/modules.py
pjs/old_utils.py
pjs/scoping.py
pjs/small.py
pjs/special.py
pjs/templates.py
pjs/utils.py
pjs/data/ast_nodes.txt
pjs/data/js_reserved.txt
pjs/data/pjslib.js
pjs/jslib/__builtin__.js
pjs/jslib/classes.js
pjs/jslib/functions.js
pjs/jslib/modules.js
pjs/templates/template.html
pjs/templates/template.js
pjs/templates/template.ss.js