Metadata-Version: 1.1
Name: PJs
Version: 0.0.2
Summary: kinda like pyjamas, but quicker, cleaner, and easier. has the goal of generating readable, usable *robust* javascript code from python code
Home-page: http://jaredforsyth.com/projects/pjs/
Author: Jared Forsyth
Author-email: jared@jaredforsyth.com
License: UNKNOWN
Platform: UNKNOWN
Classifier: Programming Language :: Python :: 2.7
